{
    "evolution": {
        "index": {},
        "uniform": {},
        "random": {},
        "selectBynasg2": {
            "range": {},
            "append": {},
            "array": {},
            "dominate": {
                "final_count": {
                    "zeros": {},
                    "range": {},
                    "append": {},
                    "count_vgij": {
                        "range": {},
                        "append": {},
                        "array": {},
                        "count_var2t": {
                            "range": {}
                        },
                        "sum": {},
                        "zeros": {}
                    },
                    "count_similar": {
                        "sqrt": {}
                    },
                    "count_alle": {
                        "range": {},
                        "append": {},
                        "count_vig": {
                            "range": {},
                            "abs": {},
                            "sum": {},
                            "array": {}
                        },
                        "multiply": {},
                        "countP": {
                            "range": {},
                            "append": {},
                            "sum": {},
                            "array": {}
                        }
                    },
                    "count_r": {
                        "range": {},
                        "multiply": {},
                        "array": {},
                        "count_hes": {
                            "max": {},
                            "array": {},
                            "range": {},
                            "min": {}
                        },
                        "print": {},
                        "abs": {},
                        "count_fuzz": {
                            "max": {},
                            "array": {},
                            "range": {},
                            "min": {}
                        }
                    },
                    "count_mcov": {},
                    "multi_add": {
                        "inside_proc": {
                            "abs": {}
                        },
                        "sum": {}
                    },
                    "count_vig": {
                        "range": {},
                        "abs": {},
                        "sum": {},
                        "array": {}
                    },
                    "count_var": {
                        "range": {}
                    },
                    "len": {}
                },
                "copy": {}
            },
            "index": {},
            "len": {}
        },
        "remove": {},
        "addto1": {
            "range": {},
            "sum": {},
            "len": {}
        },
        "append": {},
        "wakeup": {
            "remove": {},
            "list": {},
            "range": {},
            "sample": {},
            "len": {}
        },
        "copy": {},
        "final_count": {
            "zeros": {},
            "range": {},
            "append": {},
            "count_vgij": {
                "range": {},
                "append": {},
                "array": {},
                "count_var2t": {
                    "range": {}
                },
                "sum": {},
                "zeros": {}
            },
            "count_similar": {
                "sqrt": {}
            },
            "count_alle": {
                "range": {},
                "append": {},
                "count_vig": {
                    "range": {},
                    "abs": {},
                    "sum": {},
                    "array": {}
                },
                "multiply": {},
                "countP": {
                    "range": {},
                    "append": {},
                    "sum": {},
                    "array": {}
                }
            },
            "count_r": {
                "range": {},
                "multiply": {},
                "array": {},
                "count_hes": {
                    "max": {},
                    "array": {},
                    "range": {},
                    "min": {}
                },
                "print": {},
                "abs": {},
                "count_fuzz": {
                    "max": {},
                    "array": {},
                    "range": {},
                    "min": {}
                }
            },
            "count_mcov": {},
            "multi_add": {
                "inside_proc": {
                    "abs": {}
                },
                "sum": {}
            },
            "count_vig": {
                "range": {},
                "abs": {},
                "sum": {},
                "array": {}
            },
            "count_var": {
                "range": {}
            },
            "len": {}
        },
        "wake_s": {
            "remove": {},
            "list": {},
            "sample": {},
            "range": {}
        },
        "min": {},
        "select_newpop": {
            "range": {},
            "append": {},
            "copy": {},
            "count_congestion": {
                "zeros": {},
                "range": {},
                "append": {},
                "list": {},
                "copy": {},
                "sorted": {},
                "final_count": {
                    "zeros": {},
                    "range": {},
                    "append": {},
                    "count_vgij": {
                        "range": {},
                        "append": {},
                        "array": {},
                        "count_var2t": {
                            "range": {}
                        },
                        "sum": {},
                        "zeros": {}
                    },
                    "count_similar": {
                        "sqrt": {}
                    },
                    "count_alle": {
                        "range": {},
                        "append": {},
                        "count_vig": {
                            "range": {},
                            "abs": {},
                            "sum": {},
                            "array": {}
                        },
                        "multiply": {},
                        "countP": {
                            "range": {},
                            "append": {},
                            "sum": {},
                            "array": {}
                        }
                    },
                    "count_r": {
                        "range": {},
                        "multiply": {},
                        "array": {},
                        "count_hes": {
                            "max": {},
                            "array": {},
                            "range": {},
                            "min": {}
                        },
                        "print": {},
                        "abs": {},
                        "count_fuzz": {
                            "max": {},
                            "array": {},
                            "range": {},
                            "min": {}
                        }
                    },
                    "count_mcov": {},
                    "multi_add": {
                        "inside_proc": {
                            "abs": {}
                        },
                        "sum": {}
                    },
                    "count_vig": {
                        "range": {},
                        "abs": {},
                        "sum": {},
                        "array": {}
                    },
                    "count_var": {
                        "range": {}
                    },
                    "len": {}
                },
                "zip": {},
                "len": {}
            },
            "final_count": {
                "zeros": {},
                "range": {},
                "append": {},
                "count_vgij": {
                    "range": {},
                    "append": {},
                    "array": {},
                    "count_var2t": {
                        "range": {}
                    },
                    "sum": {},
                    "zeros": {}
                },
                "count_similar": {
                    "sqrt": {}
                },
                "count_alle": {
                    "range": {},
                    "append": {},
                    "count_vig": {
                        "range": {},
                        "abs": {},
                        "sum": {},
                        "array": {}
                    },
                    "multiply": {},
                    "countP": {
                        "range": {},
                        "append": {},
                        "sum": {},
                        "array": {}
                    }
                },
                "count_r": {
                    "range": {},
                    "multiply": {},
                    "array": {},
                    "count_hes": {
                        "max": {},
                        "array": {},
                        "range": {},
                        "min": {}
                    },
                    "print": {},
                    "abs": {},
                    "count_fuzz": {
                        "max": {},
                        "array": {},
                        "range": {},
                        "min": {}
                    }
                },
                "count_mcov": {},
                "multi_add": {
                    "inside_proc": {
                        "abs": {}
                    },
                    "sum": {}
                },
                "count_vig": {
                    "range": {},
                    "abs": {},
                    "sum": {},
                    "array": {}
                },
                "count_var": {
                    "range": {}
                },
                "len": {}
            },
            "len": {}
        },
        "sum": {},
        "print": {},
        "len": {},
        "range": {},
        "list": {},
        "max": {},
        "pop_init": {
            "addto1": {
                "range": {},
                "sum": {},
                "len": {}
            },
            "range": {},
            "append": {},
            "uniform": {}
        },
        "zip": {},
        "sample": {}
    }
}